rtds_action/__init__.py
rtds_action/rtds_action.py
rtds_action/rtds_action_version.py
rtds_action-1.1.0.dist-info/LICENSE
rtds_action-1.1.0.dist-info/METADATA
rtds_action-1.1.0.dist-info/WHEEL
rtds_action-1.1.0.dist-info/top_level.txt
rtds_action-1.1.0.dist-info/RECORD
