Metadata-Version: 2.1
Name: rtds-action
Version: 1.1.0
Summary: Interface GitHub Actions and ReadTheDocs
Home-page: https://github.com/dfm/rtds-action
Author: Daniel Foreman-Mackey
Author-email: foreman.mackey@gmail.com
Maintainer: Daniel Foreman-Mackey
Maintainer-email: foreman.mackey@gmail.com
License: MIT
Classifier: Development Status :: 4 - Beta
Classifier: Intended Audience :: Developers
Classifier: License :: OSI Approved :: MIT License
Classifier: Operating System :: OS Independent
Classifier: Programming Language :: Python
Classifier: Programming Language :: Python :: 3
License-File: LICENSE
Requires-Dist: sphinx (>=1.7.5)
Requires-Dist: setuptools (>=40.6.0)
Requires-Dist: setuptools-scm
Requires-Dist: requests
Provides-Extra: dev
Requires-Dist: pre-commit ; extra == 'dev'
Requires-Dist: black ; extra == 'dev'
Requires-Dist: isort ; extra == 'dev'
Requires-Dist: toml ; extra == 'dev'
Requires-Dist: flake8 ; extra == 'dev'
Requires-Dist: jupytext ; extra == 'dev'
Requires-Dist: jupyterlab ; extra == 'dev'
Requires-Dist: pep517 ; extra == 'dev'
Requires-Dist: twine ; extra == 'dev'
Provides-Extra: docs
